{"trial_id": "0197", "hyperparameters": {"space": [{"class_name": "Int", "config": {"name": "conv_filters", "default": null, "conditions": [], "min_value": 32, "max_value": 128, "step": 16, "sampling": "linear"}}, {"class_name": "Int", "config": {"name": "conv_kernel_size", "default": null, "conditions": [], "min_value": 2, "max_value": 5, "step": 1, "sampling": "linear"}}, {"class_name": "Int", "config": {"name": "max_pool_size", "default": null, "conditions": [], "min_value": 2, "max_value": 4, "step": 1, "sampling": "linear"}}, {"class_name": "Int", "config": {"name": "dense_units", "default": null, "conditions": [], "min_value": 32, "max_value": 128, "step": 16, "sampling": "linear"}}, {"class_name": "Choice", "config": {"name": "learning_rate", "default": 0.001, "conditions": [], "values": [0.001, 0.01, 0.1], "ordered": true}}], "values": {"conv_filters": 80, "conv_kernel_size": 3, "max_pool_size": 3, "dense_units": 128, "learning_rate": 0.001, "tuner/epochs": 12, "tuner/initial_epoch": 0, "tuner/bracket": 2, "tuner/round": 0}}, "metrics": {"metrics": {"loss": {"direction": "min", "observations": [{"value": [0.4105607569217682], "step": 9}]}, "accuracy": {"direction": "max", "observations": [{"value": [0.8073166608810425], "step": 9}]}, "val_loss": {"direction": "min", "observations": [{"value": [0.422000914812088], "step": 9}]}, "val_accuracy": {"direction": "max", "observations": [{"value": [0.806750476360321], "step": 9}]}}}, "score": 0.806750476360321, "best_step": 9, "status": "COMPLETED", "message": null}